pyriodic_backend/__init__.py
pyriodic_backend/backend.py
pyriodic_backend/entities.py
pyriodic_backend/protocols.py
pyriodic_backend/pyriodic_backend.py
pyriodic_backend/tests/__init__.py
pyriodic_backend/tests/test.html
pyriodic_backend/tests/test_all.py
pyriodic_backend-0.2.0.dist-info/METADATA
pyriodic_backend-0.2.0.dist-info/WHEEL
pyriodic_backend-0.2.0.dist-info/licenses/COPYING
pyriodic_backend-0.2.0.dist-info/RECORD
