Metadata-Version: 2.4
Name: pyriodic_backend
Version: 0.2.0
Summary: A backend for the small web
Project-URL: Homepage, https://codeberg.org/stfn/pyriodic-backend
Project-URL: Issues, https://codeberg.org/stfn/pyriodic-backend/issues
Author-email: STFN <stfndev@protonmail.com>
License-Expression: GPL-3.0-or-later
License-File: COPYING
Classifier: Operating System :: OS Independent
Classifier: Programming Language :: Python :: 3
Requires-Python: >=3.9
Requires-Dist: beautifulsoup4>4.13
Requires-Dist: pydantic>2.11
